eventeditor/__init__.py
eventeditor/__main__.py
eventeditor/_version.py
eventeditor/actor_json.py
eventeditor/actor_model.py
eventeditor/actor_string_list_model.py
eventeditor/actor_string_list_view.py
eventeditor/actor_view.py
eventeditor/ai.py
eventeditor/autosave.py
eventeditor/container_model.py
eventeditor/container_view.py
eventeditor/data_editors.py
eventeditor/entry_point_model.py
eventeditor/event_branch_editors.py
eventeditor/event_chooser_dialog.py
eventeditor/event_edit_dialog.py
eventeditor/event_fork_chooser_dialog.py
eventeditor/event_model.py
eventeditor/event_view.py
eventeditor/flow_data.py
eventeditor/flowchart_tools.py
eventeditor/flowchart_view.py
eventeditor/search_bar.py
eventeditor/util.py
eventeditor_GPT-1.3.8.dist-info/LICENSE
eventeditor_GPT-1.3.8.dist-info/METADATA
eventeditor_GPT-1.3.8.dist-info/WHEEL
eventeditor_GPT-1.3.8.dist-info/entry_points.txt
eventeditor_GPT-1.3.8.dist-info/top_level.txt
eventeditor_GPT-1.3.8.dist-info/RECORD
