Metadata-Version: 2.1
Name: eventeditor-GPT
Version: 1.3.8
Summary: Event editor for Breath of the Wild and Tears of the Kingdon
Home-page: https://github.com/leoetlino/event-editor
Author: leoetlino
Author-email: leo@leolam.fr
Classifier: License :: OSI Approved :: GNU General Public License v2 or later (GPLv2+)
Classifier: Operating System :: OS Independent
Classifier: Programming Language :: Python :: 3 :: Only
Requires-Python: >=3.6
License-File: LICENSE
Requires-Dist: evfl ~=1.1
Requires-Dist: pyqt5-sip ~=12.7
Requires-Dist: pyqtwebengine ~=5.14
Requires-Dist: PyYAML ~=5.1
Requires-Dist: aamp ~=1.0
Requires-Dist: byml ~=2.0
Requires-Dist: oead ~=1.1
